hatch_semver/__about__.py
hatch_semver/__init__.py
hatch_semver/bump_instruction.py
hatch_semver/errors.py
hatch_semver/semver_scheme.py
hatch_semver/plugin/__init__.py
hatch_semver/plugin/hooks.py
hatch_semver-2.0.2.dist-info/METADATA
hatch_semver-2.0.2.dist-info/WHEEL
hatch_semver-2.0.2.dist-info/entry_points.txt
hatch_semver-2.0.2.dist-info/licenses/LICENSE
hatch_semver-2.0.2.dist-info/RECORD
