Metadata-Version: 2.1
Name: hatch-semver
Version: 2.0.2
Summary: Hatch plugin for semver versioning scheme
Project-URL: Homepage, https://fleetingbytes.github.io/hatch-semver/
Project-URL: Repository, https://github.com/fleetingbytes/hatch-semver
Project-URL: Issues, https://github.com/fleetingbytes/hatch-semver/issues
Project-URL: PyPI, https://pypi.org/project/hatch-semver/
Author-email: Sven Siegmund <sven.siegmund@gmail.com>
License-Expression: MIT
License-File: LICENSE
Keywords: development,hatch,plugin,version,versioning
Classifier: Development Status :: 5 - Production/Stable
Classifier: Framework :: Hatch
Classifier: Intended Audience :: Developers
Classifier: License :: OSI Approved :: MIT License
Classifier: Natural Language :: English
Classifier: Operating System :: MacOS :: MacOS X
Classifier: Operating System :: Microsoft :: Windows
Classifier: Operating System :: OS Independent
Classifier: Operating System :: POSIX :: Linux
Classifier: Programming Language :: Python :: 3.9
Classifier: Topic :: Software Development
Requires-Python: >=3.9
Requires-Dist: hatchling
Requires-Dist: semver
